lpa/xrd/__init__.py
lpa/xrd/code.py
lpa/xrd/run.py
lpa/xrd/xrd/Makefile
lpa/xrd/xrd/kernels.cl
lpa/xrd/xrd/lpa_xrd_simulator.c
lpa/xrd/xrd/headers/compute_performance.h
lpa/xrd/xrd/headers/create_kernel_1.h
lpa/xrd/xrd/headers/create_kernel_2.h
lpa/xrd/xrd/headers/define_opencl_accelerator.h
lpa/xrd/xrd/headers/export_output_data.h
lpa/xrd/xrd/headers/generate_random_points.h
lpa/xrd/xrd/headers/header.h
lpa/xrd/xrd/headers/load_input_data.h
lpa/xrd/xrd/headers/results_kernel_1.h
lpa/xrd/xrd/headers/results_kernel_2.h
lpa_xrd-1.0.1.dist-info/LICENSE.txt
lpa_xrd-1.0.1.dist-info/METADATA
lpa_xrd-1.0.1.dist-info/WHEEL
lpa_xrd-1.0.1.dist-info/top_level.txt
lpa_xrd-1.0.1.dist-info/RECORD
