Metadata-Version: 2.1
Name: lpa-xrd
Version: 1.0.1
Summary: Tools for the simulation of x-ray diffraction.
Home-page: https://github.com/DunstanBecht/lpa-xrd
Author: Dunstan Becht
Author-email: dunstan@becht.network
License: UNKNOWN
Project-URL: Bug Tracker, https://github.com/DunstanBecht/lpa-xrd/issues
Platform: UNKNOWN
Classifier: Programming Language :: Python :: 3
Classifier: License :: CC0 1.0 Universal (CC0 1.0) Public Domain Dedication
Classifier: Operating System :: OS Independent
Classifier: Environment :: GPU
Classifier: Topic :: Scientific/Engineering :: Physics
License-File: LICENSE.txt
Requires-Dist: beartype
